{
  "_filename": "warehouse.lua",
  "_isShebang": false,
  "_isSpec": false,
  "_isTest": false,
  "_path": "modules/simulua/examples/warehouse.lua",
  "edges": [ {
    "from": 0,
    "label": "implements",
    "to": 1
  }, {
    "from": 3,
    "label": "has",
    "to": 4
  }, {
    "from": 4,
    "label": "has",
    "to": 5
  }, {
    "from": 4,
    "label": "has",
    "to": 6
  }, {
    "from": 4,
    "label": "has",
    "to": 7
  }, {
    "from": 4,
    "label": "has",
    "to": 8
  }, {
    "from": 8,
    "label": "has",
    "to": 9
  }, {
    "from": 8,
    "label": "has",
    "to": 10
  }, {
    "from": 8,
    "label": "has",
    "to": 11
  }, {
    "from": 8,
    "label": "has",
    "to": 12
  }, {
    "from": 12,
    "label": "has",
    "to": 13
  }, {
    "from": 3,
    "label": "has",
    "to": 14
  }, {
    "from": 15,
    "label": "has",
    "to": 16
  }, {
    "from": 16,
    "label": "has",
    "to": 17
  }, {
    "from": 17,
    "label": "has",
    "to": 18
  }, {
    "from": 17,
    "label": "has",
    "to": 10
  }, {
    "from": 17,
    "label": "has",
    "to": 19
  }, {
    "from": 17,
    "label": "has",
    "to": 20
  }, {
    "from": 17,
    "label": "has",
    "to": 21
  }, {
    "from": 16,
    "label": "has",
    "to": 22
  }, {
    "from": 15,
    "label": "has",
    "to": 23
  }, {
    "from": 24,
    "label": "has",
    "to": 25
  }, {
    "from": 24,
    "label": "has",
    "to": 13
  }, {
    "from": 24,
    "label": "has",
    "to": 26
  }, {
    "from": 24,
    "label": "has",
    "to": 27
  }, {
    "from": 24,
    "label": "has",
    "to": 28
  }, {
    "from": 24,
    "label": "has",
    "to": 29
  }, {
    "from": 30,
    "label": "calls",
    "to": 34
  }, {
    "from": 30,
    "label": "calls",
    "to": 41
  }, {
    "from": 30,
    "label": "calls",
    "to": 37
  }, {
    "from": 30,
    "label": "calls",
    "to": 31
  }, {
    "from": 30,
    "label": "calls",
    "to": 31
  }, {
    "from": 30,
    "label": "calls",
    "to": 33
  }, {
    "from": 30,
    "label": "calls",
    "to": 33
  }, {
    "from": 30,
    "label": "calls",
    "to": 33
  }, {
    "from": 30,
    "label": "calls",
    "to": 32
  }, {
    "from": 30,
    "label": "calls",
    "to": 36
  }, {
    "from": 30,
    "label": "calls",
    "to": 35
  }, {
    "from": 30,
    "label": "calls",
    "to": 35
  }, {
    "from": 30,
    "label": "calls",
    "to": 35
  }, {
    "from": 30,
    "label": "calls",
    "to": 40
  }, {
    "from": 30,
    "label": "calls",
    "to": 40
  }, {
    "from": 30,
    "label": "calls",
    "to": 40
  }, {
    "from": 30,
    "label": "calls",
    "to": 39
  }, {
    "from": 30,
    "label": "calls",
    "to": 39
  }, {
    "from": 30,
    "label": "calls",
    "to": 38
  }, {
    "from": 30,
    "label": "calls",
    "to": 38
  }, {
    "from": 1,
    "label": "contains",
    "to": 30
  }, {
    "from": 30,
    "label": "declares",
    "to": 3
  }, {
    "from": 30,
    "label": "declares",
    "to": 15
  }, {
    "from": 30,
    "label": "declares",
    "to": 24
  }, {
    "from": 1,
    "label": "contains",
    "to": 44
  }, {
    "from": 1,
    "label": "contains",
    "to": 45
  }, {
    "from": 44,
    "label": "initializes",
    "to": 46
  }, {
    "from": 46,
    "label": "assigns",
    "to": 47
  }, {
    "from": 44,
    "label": "initializes",
    "to": 48
  }, {
    "from": 48,
    "label": "assigns",
    "to": 49
  }, {
    "from": 44,
    "label": "initializes",
    "to": 50
  }, {
    "from": 50,
    "label": "assigns",
    "to": 51
  }, {
    "from": 44,
    "label": "initializes",
    "to": 52
  }, {
    "from": 52,
    "label": "assigns",
    "to": 53
  }, {
    "from": 44,
    "label": "initializes",
    "to": 54
  }, {
    "from": 54,
    "label": "assigns",
    "to": 55
  }, {
    "from": 44,
    "label": "initializes",
    "to": 56
  }, {
    "from": 56,
    "label": "assigns",
    "to": 57
  }, {
    "from": 44,
    "label": "initializes",
    "to": 58
  }, {
    "from": 58,
    "label": "assigns",
    "to": 59
  }, {
    "from": 44,
    "label": "initializes",
    "to": 60
  }, {
    "from": 60,
    "label": "assigns",
    "to": 61
  }, {
    "from": 44,
    "label": "initializes",
    "to": 62
  }, {
    "from": 62,
    "label": "assigns",
    "to": 63
  }, {
    "from": 44,
    "label": "initializes",
    "to": 64
  }, {
    "from": 64,
    "label": "assigns",
    "to": 65
  }, {
    "from": 44,
    "label": "initializes",
    "to": 66
  }, {
    "from": 66,
    "label": "assigns",
    "to": 67
  }, {
    "from": 44,
    "label": "initializes",
    "to": 68
  }, {
    "from": 68,
    "label": "assigns",
    "to": 69
  }, {
    "from": 44,
    "label": "initializes",
    "to": 70
  }, {
    "from": 70,
    "label": "assigns",
    "to": 71
  }, {
    "from": 44,
    "label": "initializes",
    "to": 72
  }, {
    "from": 44,
    "label": "initializes",
    "to": 73
  }, {
    "from": 45,
    "label": "initializes",
    "to": 74
  }, {
    "from": 74,
    "label": "requires",
    "to": 2
  }, {
    "from": 45,
    "label": "initializes",
    "to": 75
  }, {
    "from": 75,
    "label": "requires",
    "to": 43
  }, {
    "from": 45,
    "label": "initializes",
    "to": 76
  }, {
    "from": 76,
    "label": "requires",
    "to": 42
  } ],
  "nodes": [ {
    "id": 0,
    "text": "",
    "type": "file"
  }, {
    "id": 1,
    "text": "warehouse",
    "type": "module"
  }, {
    "id": 2,
    "text": "simulua",
    "type": "module"
  }, {
    "id": 3,
    "text": "function()\r\n    while true do\r\n      simulua.hold(r:exp(arr))\r\n      arrived = arrived + 1\r\n      number = r:unifint(in1, in2)\r\n      if number > m - n then\r\n        rejected = rejected + 1\r\n      else\r\n        warehouse:update(n)\r\n        n = n + number\r\n        if simulua.idle(worker) then\r\n          simulua.activate(worker)\r\n        end\r\n      end\r\n    end\r\n  end",
    "type": "function"
  }, {
    "id": 4,
    "text": "while true do\r\n      simulua.hold(r:exp(arr))\r\n      arrived = arrived + 1\r\n      number = r:unifint(in1, in2)\r\n      if number > m - n then\r\n        rejected = rejected + 1\r\n      else\r\n        warehouse:update(n)\r\n        n = n + number\r\n        if simulua.idle(worker) then\r\n          simulua.activate(worker)\r\n        end\r\n      end\r\n    end",
    "type": "statement:while"
  }, {
    "id": 5,
    "text": "simulua.hold(r:exp(arr))",
    "type": "statement:functioncall"
  }, {
    "id": 6,
    "text": "arrived = arrived + 1",
    "type": "statement:assign"
  }, {
    "id": 7,
    "text": "number = r:unifint(in1, in2)",
    "type": "statement:assign"
  }, {
    "id": 8,
    "text": "if number > m - n then\r\n        rejected = rejected + 1\r\n      else\r\n        warehouse:update(n)\r\n        n = n + number\r\n        if simulua.idle(worker) then\r\n          simulua.activate(worker)\r\n        end\r\n      end",
    "type": "statement:if"
  }, {
    "id": 9,
    "text": "rejected = rejected + 1",
    "type": "statement:assign"
  }, {
    "id": 10,
    "text": "warehouse:update(n)",
    "type": "statement:functioncall"
  }, {
    "id": 11,
    "text": "n = n + number",
    "type": "statement:assign"
  }, {
    "id": 12,
    "text": "if simulua.idle(worker) then\r\n          simulua.activate(worker)\r\n        end",
    "type": "statement:if"
  }, {
    "id": 13,
    "text": "simulua.activate(worker)",
    "type": "statement:functioncall"
  }, {
    "id": 14,
    "text": "",
    "type": "blank lines"
  }, {
    "id": 15,
    "text": "function()\r\n    while true do\r\n      while n > 0 do\r\n        simulua.hold(r:exp(rem))\r\n        warehouse:update(n)\r\n        size = r:unifint(out1, out2)\r\n        number = size < n and size or n\r\n        n = n - number\r\n      end\r\n      simulua.passivate() -- warehouse is now empty\r\n    end\r\n  end",
    "type": "function"
  }, {
    "id": 16,
    "text": "while true do\r\n      while n > 0 do\r\n        simulua.hold(r:exp(rem))\r\n        warehouse:update(n)\r\n        size = r:unifint(out1, out2)\r\n        number = size < n and size or n\r\n        n = n - number\r\n      end\r\n      simulua.passivate() -- warehouse is now empty\r\n    end",
    "type": "statement:while"
  }, {
    "id": 17,
    "text": "while n > 0 do\r\n        simulua.hold(r:exp(rem))\r\n        warehouse:update(n)\r\n        size = r:unifint(out1, out2)\r\n        number = size < n and size or n\r\n        n = n - number\r\n      end",
    "type": "statement:while"
  }, {
    "id": 18,
    "text": "simulua.hold(r:exp(rem))",
    "type": "statement:functioncall"
  }, {
    "id": 19,
    "text": "size = r:unifint(out1, out2)",
    "type": "statement:assign"
  }, {
    "id": 20,
    "text": "number = size < n and size or n",
    "type": "statement:assign"
  }, {
    "id": 21,
    "text": "n = n - number",
    "type": "statement:assign"
  }, {
    "id": 22,
    "text": "simulua.passivate()",
    "type": "statement:functioncall"
  }, {
    "id": 23,
    "text": "",
    "type": "blank lines"
  }, {
    "id": 24,
    "text": "function()\r\n  simulua.activate(arrivals)\r\n  simulua.activate(worker)\r\n  simulua.hold(simperiod)\r\n  print(string.format(\"Proportion of rejected batches: %.2f\",\r\n    rejected / arrived))\r\n  print(string.format(\"Average no. of items in warehouse: %.2f\",\r\n    warehouse.mean))\r\nend",
    "type": "function"
  }, {
    "id": 25,
    "text": "simulua.activate(arrivals)",
    "type": "statement:functioncall"
  }, {
    "id": 26,
    "text": "simulua.hold(simperiod)",
    "type": "statement:functioncall"
  }, {
    "id": 27,
    "text": "print(string.format(\"Proportion of rejected batches: %.2f\",\r\n    rejected / arrived))",
    "type": "statement:functioncall"
  }, {
    "id": 28,
    "text": "print(string.format(\"Average no. of items in warehouse: %.2f\",\r\n    warehouse.mean))",
    "type": "statement:functioncall"
  }, {
    "id": 29,
    "text": "",
    "type": "blank lines"
  }, {
    "id": 30,
    "text": "",
    "type": "function container"
  }, {
    "id": 31,
    "text": "function process (task, att)\r\n  local p = setmetatable(att or {}, procmt)\r\n  thread[p] = create(task)\r\n  return p\r\nend",
    "type": "function"
  }, {
    "id": 32,
    "text": "function idle (proc)\r\n  local p = checkprocess(proc)\r\n  return isidle[p] or events:get(p) == nil -- idle or not scheduled yet?\r\nend",
    "type": "function"
  }, {
    "id": 33,
    "text": "function hold (delay) yield(\"hold\", delay) end",
    "type": "function"
  }, {
    "id": 34,
    "text": "function passivate () yield(\"cancel\", _current) end",
    "type": "function"
  }, {
    "id": 35,
    "text": "function activate (proc, d, after)\r\n  yield(\"activate\", proc, d, after)\r\nend",
    "type": "function"
  }, {
    "id": 36,
    "text": "function start (task)\r\n  events, isidle, main = heap(), {}, process(task)\r\n  events:insert(0, main)\r\n  local active, msg = resume(scheduler())\r\n  assert(active, msg)\r\n  if msg ~= nil then error(msg) end\r\nend",
    "type": "function"
  }, {
    "id": 37,
    "text": "function accumulator ()\r\n  return setmetatable({last = 0, mean = 0}, _acc)\r\nend",
    "type": "function"
  }, {
    "id": 38,
    "text": "format",
    "type": "global function"
  }, {
    "id": 39,
    "text": "print",
    "type": "global function"
  }, {
    "id": 40,
    "text": "require",
    "type": "global function"
  }, {
    "id": 41,
    "text": "rng",
    "type": "global function"
  }, {
    "id": 42,
    "text": "queue",
    "type": "module"
  }, {
    "id": 43,
    "text": "rng",
    "type": "module"
  }, {
    "id": 44,
    "text": "",
    "type": "variable container"
  }, {
    "id": 45,
    "text": "",
    "type": "require container"
  }, {
    "id": 46,
    "text": "",
    "type": "local variable"
  }, {
    "id": 47,
    "text": "",
    "type": "n/a"
  }, {
    "id": 48,
    "text": "",
    "type": "local variable"
  }, {
    "id": 49,
    "text": "",
    "type": "n/a"
  }, {
    "id": 50,
    "text": "",
    "type": "local variable"
  }, {
    "id": 51,
    "text": "",
    "type": "number"
  }, {
    "id": 52,
    "text": "",
    "type": "local variable"
  }, {
    "id": 53,
    "text": "",
    "type": "number"
  }, {
    "id": 54,
    "text": "",
    "type": "local variable"
  }, {
    "id": 55,
    "text": "",
    "type": "number"
  }, {
    "id": 56,
    "text": "",
    "type": "local variable"
  }, {
    "id": 57,
    "text": "",
    "type": "number"
  }, {
    "id": 58,
    "text": "",
    "type": "local variable"
  }, {
    "id": 59,
    "text": "",
    "type": "number"
  }, {
    "id": 60,
    "text": "",
    "type": "local variable"
  }, {
    "id": 61,
    "text": "",
    "type": "number"
  }, {
    "id": 62,
    "text": "",
    "type": "local variable"
  }, {
    "id": 63,
    "text": "",
    "type": "number"
  }, {
    "id": 64,
    "text": "",
    "type": "local variable"
  }, {
    "id": 65,
    "text": "",
    "type": "number"
  }, {
    "id": 66,
    "text": "",
    "type": "local variable"
  }, {
    "id": 67,
    "text": "",
    "type": "number"
  }, {
    "id": 68,
    "text": "",
    "type": "local variable"
  }, {
    "id": 69,
    "text": "",
    "type": "number"
  }, {
    "id": 70,
    "text": "",
    "type": "local variable"
  }, {
    "id": 71,
    "text": "",
    "type": "number"
  }, {
    "id": 72,
    "text": "",
    "type": "local variable"
  }, {
    "id": 73,
    "text": "",
    "type": "local variable"
  }, {
    "id": 74,
    "text": "",
    "type": "require local variable"
  }, {
    "id": 75,
    "text": "",
    "type": "require local variable"
  }, {
    "id": 76,
    "text": "",
    "type": "require local variable"
  } ]
}